setup.py
src/HHH/__init__.py
src/HHH/brave/__init__.py
src/HHH/brave/sunny/__init__.py
src/HHH/brave/sunny/information.py
src/HHH/brave/sunny/message.py
src/HHH_echo.egg-info/PKG-INFO
src/HHH_echo.egg-info/SOURCES.txt
src/HHH_echo.egg-info/dependency_links.txt
src/HHH_echo.egg-info/top_level.txt