Metadata-Version: 2.1
Name: HHH-echo
Version: 0.1
Summary: 袁力祈,何慧华
Author: HHH
License: UNKNOWN
Platform: UNKNOWN
